{ "type": "FeatureCollection", "crs": { "type": "name", "properties": { "name": "urn:ogc:def:crs:OGC:1.3:CRS84" } }, "features": [ 
{ "type": "Feature", "properties": { "Name": "William Falk-Wallace", "Description": "Thu Sep 19 11:40:14 EDT 2013; Location Accuracy: 65.000000" }, "geometry": { "type": "Point", "coordinates": [ -73.969653, 40.800806, 0.0 ] } },
{ "type": "Feature", "properties": { "Name": "William Falk-Wallace", "Description": "Thu Sep 19 11:38:35 EDT 2013; Location Accuracy: 65.000000" }, "geometry": { "type": "Point", "coordinates": [ -73.969685, 40.800828, 0.0 ] } },
{ "type": "Feature", "properties": { "Name": "William Falk-Wallace", "Description": "Thu Sep 19 11:30:05 EDT 2013; Location Accuracy: 65.000000" }, "geometry": { "type": "Point", "coordinates": [ -73.969681, 40.800829, 0.0 ] } },
{ "type": "Feature", "properties": { "Name": "William Falk-Wallace", "Description": "Wed Sep 18 22:46:24 EDT 2013; Location Accuracy: 65.000000" }, "geometry": { "type": "Point", "coordinates": [ -73.969675, 40.800824, 0.0 ] } },
{ "type": "Feature", "properties": { "Name": "William Falk-Wallace", "Description": "Wed Sep 18 22:45:07 EDT 2013; Location Accuracy: 65.000000" }, "geometry": { "type": "Point", "coordinates": [ -73.969675, 40.800824, 0.0 ] } },
{ "type": "Feature", "properties": { "Name": "William Falk-Wallace", "Description": "Wed Sep 18 22:43:05 EDT 2013; Location Accuracy: 65.000000" }, "geometry": { "type": "Point", "coordinates": [ -73.969675, 40.800824, 0.0 ] } }
]}
